cdk8s_external_dns_route53/__init__.py
cdk8s_external_dns_route53/py.typed
cdk8s_external_dns_route53/_jsii/__init__.py
cdk8s_external_dns_route53/_jsii/cdk8s-external-dns-route53@0.1.4.jsii.tgz
cdk8s_external_dns_route53-0.1.4.dist-info/LICENSE
cdk8s_external_dns_route53-0.1.4.dist-info/METADATA
cdk8s_external_dns_route53-0.1.4.dist-info/WHEEL
cdk8s_external_dns_route53-0.1.4.dist-info/top_level.txt
cdk8s_external_dns_route53-0.1.4.dist-info/RECORD
